<?xml version="1.0" encoding="UTF-8" standalone="yes"?>
<QualityMeasureDocument xmlns="urn:hl7-org:v3" xmlns:cql-ext="urn:hhs-cql:hqmf-n1-extensions:v1"
                        xmlns:xsi="http://www.w3.org/2001/XMLSchema-instance">

      <!--
            **************************************************************
            Measure Details Section
            **************************************************************
        -->

      <typeId extension="POQM_HD000001UV02" root="2.16.840.1.113883.1.3"/>
   <templateId>
      <item extension="2021-02-01" root="2.16.840.1.113883.10.20.28.1.2"/>
   </templateId>
   <id root="2c928085-7b2a-eb52-017b-56761e0218d0"/>
   <code code="57024-2" codeSystem="2.16.840.1.113883.6.1">
      <displayName value="Health Quality Measure Document"/>
   </code>
   <title value="Diabetes: Hemoglobin A1c (HbA1c) Poor Control (&gt; 9%)"/>
   <text
         value="Percentage of patients 18-75 years of age with diabetes who had hemoglobin A1c &gt; 9.0% during the measurement period"/>
   <statusCode code="COMPLETED"/>
   <setId root="f2986519-5a4e-4149-a8f2-af0a1dc7f6bc"/>
   <versionNumber value="11.0.000"/>
   <author>
      <responsibleParty classCode="ASSIGNED">
         <representedResponsibleOrganization classCode="ORG" determinerCode="INSTANCE">
            <id>
               <item root="2.16.840.1.113883.3.464"/>
            </id>
            <name>
               <item>
                  <part value="National Committee for Quality Assurance"/>
               </item>
            </name>
         </representedResponsibleOrganization>
      </responsibleParty>
   </author>
   <custodian>
      <responsibleParty classCode="ASSIGNED">
         <representedResponsibleOrganization classCode="ORG" determinerCode="INSTANCE">
            <id>
               <item root="40"/>
            </id>
            <name>
               <item>
                  <part value="National Committee for Quality Assurance"/>
               </item>
            </name>
         </representedResponsibleOrganization>
      </responsibleParty>
   </custodian>
   <!--ONC Administrative Sex-->
     	 <definition>
      <valueSet classCode="OBS" moodCode="DEF">
         <id root="2.16.840.1.113762.1.4.1"/>
         <title value="ONC Administrative Sex"/>
      </valueSet>
   </definition>
   <!--Telephone Visits-->
     	 <definition>
      <valueSet classCode="OBS" moodCode="DEF">
         <id root="2.16.840.1.113883.3.464.1003.101.12.1080"/>
         <title value="Telephone Visits"/>
      </valueSet>
   </definition>
   <!--Nutrition Services-->
     	 <definition>
      <valueSet classCode="OBS" moodCode="DEF">
         <id root="2.16.840.1.113883.3.464.1003.1006"/>
         <title value="Nutrition Services"/>
      </valueSet>
   </definition>
   <!--Acute Inpatient-->
     	 <definition>
      <valueSet classCode="OBS" moodCode="DEF">
         <id root="2.16.840.1.113883.3.464.1003.101.12.1083"/>
         <title value="Acute Inpatient"/>
      </valueSet>
   </definition>
   <!--Encounter Inpatient-->
     	 <definition>
      <valueSet classCode="OBS" moodCode="DEF">
         <id root="2.16.840.1.113883.3.666.5.307"/>
         <title value="Encounter Inpatient"/>
      </valueSet>
   </definition>
   <!--Hospice Care Ambulatory-->
     	 <definition>
      <valueSet classCode="OBS" moodCode="DEF">
         <id root="2.16.840.1.113883.3.526.3.1584"/>
         <title value="Hospice Care Ambulatory"/>
      </valueSet>
   </definition>
   <!--Frailty Device-->
     	 <definition>
      <valueSet classCode="OBS" moodCode="DEF">
         <id root="2.16.840.1.113883.3.464.1003.118.12.1300"/>
         <title value="Frailty Device"/>
      </valueSet>
   </definition>
   <!--Frailty Encounter-->
     	 <definition>
      <valueSet classCode="OBS" moodCode="DEF">
         <id root="2.16.840.1.113883.3.464.1003.101.12.1088"/>
         <title value="Frailty Encounter"/>
      </valueSet>
   </definition>
   <!--HbA1c Laboratory Test-->
     	 <definition>
      <valueSet classCode="OBS" moodCode="DEF">
         <id root="2.16.840.1.113883.3.464.1003.198.12.1013"/>
         <title value="HbA1c Laboratory Test"/>
      </valueSet>
   </definition>
   <!--Preventive Care Services Established Office Visit, 18 and Up-->
     	 <definition>
      <valueSet classCode="OBS" moodCode="DEF">
         <id root="2.16.840.1.113883.3.464.1003.101.12.1025"/>
         <title value="Preventive Care Services Established Office Visit, 18 and Up"/>
      </valueSet>
   </definition>
   <!--Frailty Diagnosis-->
     	 <definition>
      <valueSet classCode="OBS" moodCode="DEF">
         <id root="2.16.840.1.113883.3.464.1003.113.12.1074"/>
         <title value="Frailty Diagnosis"/>
      </valueSet>
   </definition>
   <!--Home Healthcare Services-->
     	 <definition>
      <valueSet classCode="OBS" moodCode="DEF">
         <id root="2.16.840.1.113883.3.464.1003.101.12.1016"/>
         <title value="Home Healthcare Services"/>
      </valueSet>
   </definition>
   <!--Race-->
     	 <definition>
      <valueSet classCode="OBS" moodCode="DEF">
         <id root="2.16.840.1.114222.4.11.836"/>
         <title value="Race"/>
      </valueSet>
   </definition>
   <!--Office Visit-->
     	 <definition>
      <valueSet classCode="OBS" moodCode="DEF">
         <id root="2.16.840.1.113883.3.464.1003.101.12.1001"/>
         <title value="Office Visit"/>
      </valueSet>
   </definition>
   <!--Payer-->
     	 <definition>
      <valueSet classCode="OBS" moodCode="DEF">
         <id root="2.16.840.1.114222.4.11.3591"/>
         <title value="Payer"/>
      </valueSet>
   </definition>
   <!--Nonacute Inpatient-->
     	 <definition>
      <valueSet classCode="OBS" moodCode="DEF">
         <id root="2.16.840.1.113883.3.464.1003.101.12.1084"/>
         <title value="Nonacute Inpatient"/>
      </valueSet>
   </definition>
   <!--Dementia Medications-->
     	 <definition>
      <valueSet classCode="OBS" moodCode="DEF">
         <id root="2.16.840.1.113883.3.464.1003.196.12.1510"/>
         <title value="Dementia Medications"/>
      </valueSet>
   </definition>
   <!--Palliative Care Intervention-->
     	 <definition>
      <valueSet classCode="OBS" moodCode="DEF">
         <id root="2.16.840.1.113883.3.464.1003.198.12.1135"/>
         <title value="Palliative Care Intervention"/>
      </valueSet>
   </definition>
   <!--Palliative Care Encounter-->
     	 <definition>
      <valueSet classCode="OBS" moodCode="DEF">
         <id root="2.16.840.1.113883.3.464.1003.101.12.1090"/>
         <title value="Palliative Care Encounter"/>
      </valueSet>
   </definition>
   <!--Frailty Symptom-->
     	 <definition>
      <valueSet classCode="OBS" moodCode="DEF">
         <id root="2.16.840.1.113883.3.464.1003.113.12.1075"/>
         <title value="Frailty Symptom"/>
      </valueSet>
   </definition>
   <!--Observation-->
     	 <definition>
      <valueSet classCode="OBS" moodCode="DEF">
         <id root="2.16.840.1.113883.3.464.1003.101.12.1086"/>
         <title value="Observation"/>
      </valueSet>
   </definition>
   <!--Annual Wellness Visit-->
     	 <definition>
      <valueSet classCode="OBS" moodCode="DEF">
         <id root="2.16.840.1.113883.3.526.3.1240"/>
         <title value="Annual Wellness Visit"/>
      </valueSet>
   </definition>
   <!--Outpatient-->
     	 <definition>
      <valueSet classCode="OBS" moodCode="DEF">
         <id root="2.16.840.1.113883.3.464.1003.101.12.1087"/>
         <title value="Outpatient"/>
      </valueSet>
   </definition>
   <!--Ethnicity-->
     	 <definition>
      <valueSet classCode="OBS" moodCode="DEF">
         <id root="2.16.840.1.114222.4.11.837"/>
         <title value="Ethnicity"/>
      </valueSet>
   </definition>
   <!--Emergency Department Visit-->
     	 <definition>
      <valueSet classCode="OBS" moodCode="DEF">
         <id root="2.16.840.1.113883.3.464.1003.101.12.1010"/>
         <title value="Emergency Department Visit"/>
      </valueSet>
   </definition>
   <!--Preventive Care Services Initial Office Visit, 18 and Up-->
     	 <definition>
      <valueSet classCode="OBS" moodCode="DEF">
         <id root="2.16.840.1.113883.3.464.1003.101.12.1023"/>
         <title value="Preventive Care Services Initial Office Visit, 18 and Up"/>
      </valueSet>
   </definition>
   <!--Hospice Encounter-->
     	 <definition>
      <valueSet classCode="OBS" moodCode="DEF">
         <id root="2.16.840.1.113883.3.464.1003.1003"/>
         <title value="Hospice Encounter"/>
      </valueSet>
   </definition>
   <!--Diabetes-->
     	 <definition>
      <valueSet classCode="OBS" moodCode="DEF">
         <id root="2.16.840.1.113883.3.464.1003.103.12.1001"/>
         <title value="Diabetes"/>
      </valueSet>
   </definition>
   <!--Advanced Illness-->
     	 <definition>
      <valueSet classCode="OBS" moodCode="DEF">
         <id root="2.16.840.1.113883.3.464.1003.110.12.1082"/>
         <title value="Advanced Illness"/>
      </valueSet>
   </definition>
   <!--Encounter for palliative care-CODE:/CodeSystem/ICD10CM/Version/2022/Code/Z51.5/Info-->
      <definition>
      <cql-ext:code code="Z51.5" codeSystem="2.16.840.1.113883.6.90" codeSystemName="ICD10CM">
         <displayName value="Encounter for palliative care"/>
      </cql-ext:code>
   </definition>
   <!--Medical nutrition therapy; initial assessment and intervention, individual, face-to-face with the patient, each 15 minutes-CODE:/CodeSystem/CPT/Version/2021/Code/97802/Info-->
      <definition>
      <cql-ext:code code="97802" codeSystem="2.16.840.1.113883.6.12" codeSystemName="CPT">
         <displayName value="Medical nutrition therapy; initial assessment and intervention, individual, face-to-face with the patient, each 15 minutes"/>
      </cql-ext:code>
   </definition>
   <!--Medical nutrition therapy; re-assessment and intervention, individual, face-to-face with the patient, each 15 minutes-CODE:/CodeSystem/CPT/Version/2021/Code/97803/Info-->
      <definition>
      <cql-ext:code code="97803" codeSystem="2.16.840.1.113883.6.12" codeSystemName="CPT">
         <displayName value="Medical nutrition therapy; re-assessment and intervention, individual, face-to-face with the patient, each 15 minutes"/>
      </cql-ext:code>
   </definition>
   <!--Medical nutrition therapy; reassessment and subsequent intervention(s) following second referral in same year for change in diagnosis, medical condition or treatment regimen (including additional hours needed for renal disease), individual, face to face with the patient, each 15 minutes-CODE:/CodeSystem/HCPCS/Version/2022/Code/G0270/Info-->
      <definition>
      <cql-ext:code code="G0270" codeSystem="2.16.840.1.113883.6.285" codeSystemName="HCPCS">
         <displayName value="Medical nutrition therapy; reassessment and subsequent intervention(s) following second referral in same year for change in diagnosis, medical condition or treatment regimen (including additional hours needed for renal disease), individual, face to face with the patient, each 15 minutes"/>
      </cql-ext:code>
   </definition>
   <!--Functional Assessment of Chronic Illness Therapy - Palliative Care Questionnaire (FACIT-Pal)-CODE:/CodeSystem/LOINC/Version/2.71/Code/71007-9/Info-->
      <definition>
      <cql-ext:code code="71007-9" codeSystem="2.16.840.1.113883.6.1" codeSystemName="LOINC">
         <displayName value="Functional Assessment of Chronic Illness Therapy - Palliative Care Questionnaire (FACIT-Pal)"/>
      </cql-ext:code>
   </definition>
   <!--Medical nutrition therapy, reassessment and subsequent intervention(s) following second referral in same year for change in diagnosis, medical condition, or treatment regimen (including additional hours needed for renal disease), group (2 or more individuals), each 30 minutes-CODE:/CodeSystem/HCPCS/Version/2022/Code/G0271/Info-->
      <definition>
      <cql-ext:code code="G0271" codeSystem="2.16.840.1.113883.6.285" codeSystemName="HCPCS">
         <displayName value="Medical nutrition therapy, reassessment and subsequent intervention(s) following second referral in same year for change in diagnosis, medical condition, or treatment regimen (including additional hours needed for renal disease), group (2 or more individuals), each 30 minutes"/>
      </cql-ext:code>
   </definition>
   <!--Medical equipment used-CODE:/CodeSystem/LOINC/Version/2.71/Code/98181-1/Info-->
      <definition>
      <cql-ext:code code="98181-1" codeSystem="2.16.840.1.113883.6.1" codeSystemName="LOINC">
         <displayName value="Medical equipment used"/>
      </cql-ext:code>
   </definition>
   <!--Housing status-CODE:/CodeSystem/LOINC/Version/2.71/Code/71802-3/Info-->
      <definition>
      <cql-ext:code code="71802-3" codeSystem="2.16.840.1.113883.6.1" codeSystemName="LOINC">
         <displayName value="Housing status"/>
      </cql-ext:code>
   </definition>
   <!--Hospice care [Minimum Data Set]-CODE:/CodeSystem/LOINC/Version/2.71/Code/45755-6/Info-->
      <definition>
      <cql-ext:code code="45755-6" codeSystem="2.16.840.1.113883.6.1" codeSystemName="LOINC">
         <displayName value="Hospice care [Minimum Data Set]"/>
      </cql-ext:code>
   </definition>
   <!--Medical nutrition therapy; group (2 or more individual(s)), each 30 minutes-CODE:/CodeSystem/CPT/Version/2021/Code/97804/Info-->
      <definition>
      <cql-ext:code code="97804" codeSystem="2.16.840.1.113883.6.12" codeSystemName="CPT">
         <displayName value="Medical nutrition therapy; group (2 or more individual(s)), each 30 minutes"/>
      </cql-ext:code>
   </definition>
   <!--Lives in a nursing home (finding)-CODE:/CodeSystem/SNOMEDCT/Version/2021-09/Code/160734000/Info-->
      <definition>
      <cql-ext:code code="160734000" codeSystem="2.16.840.1.113883.6.96" codeSystemName="SNOMEDCT">
         <displayName value="Lives in a nursing home (finding)"/>
      </cql-ext:code>
   </definition>
   <!--Discharge to home for hospice care (procedure)-CODE:/CodeSystem/SNOMEDCT/Version/2021-09/Code/428361000124107/Info-->
      <definition>
      <cql-ext:code code="428361000124107" codeSystem="2.16.840.1.113883.6.96"
                    codeSystemName="SNOMEDCT">
         <displayName value="Discharge to home for hospice care (procedure)"/>
      </cql-ext:code>
   </definition>
   <!--Discharge to healthcare facility for hospice care (procedure)-CODE:/CodeSystem/SNOMEDCT/Version/2021-09/Code/428371000124100/Info-->
      <definition>
      <cql-ext:code code="428371000124100" codeSystem="2.16.840.1.113883.6.96"
                    codeSystemName="SNOMEDCT">
         <displayName value="Discharge to healthcare facility for hospice care (procedure)"/>
      </cql-ext:code>
   </definition>
   <!--Yes (qualifier value)-CODE:/CodeSystem/SNOMEDCT/Version/2021-09/Code/373066001/Info-->
      <definition>
      <cql-ext:code code="373066001" codeSystem="2.16.840.1.113883.6.96" codeSystemName="SNOMEDCT">
         <displayName value="Yes (qualifier value)"/>
      </cql-ext:code>
   </definition>
   <relatedDocument typeCode="COMP">
      <expressionDocument>
         <id root="EFFB0CFA-05AF-4905-A84B-CAFBA22EE258"/>
         <text mediaType="text/cql">
            <reference value="https://emeasuretool.cms.gov/libraries/f2986519-5a4e-4149-a8f2-af0a1dc7f6bc/CMS122-v11-0-000-QDM-5-6.cql"/>
            <translation mediaType="application/elm+xml">
               <reference value="https://emeasuretool.cms.gov/libraries/f2986519-5a4e-4149-a8f2-af0a1dc7f6bc/CMS122-v11-0-000-QDM-5-6.xml"/>
            </translation>
            <translation mediaType="application/elm+json">
               <reference value="https://emeasuretool.cms.gov/libraries/f2986519-5a4e-4149-a8f2-af0a1dc7f6bc/CMS122-v11-0-000-QDM-5-6.json"/>
            </translation>
         </text>
         <setId extension="f2986519-5a4e-4149-a8f2-af0a1dc7f6bc"
                identifierName="DiabetesHemoglobinA1cHbA1cPoorControl9"
                root="https://emeasuretool.cms.gov/libraries"/>
         <versionNumber value="11.0.000"/>
      </expressionDocument>
   </relatedDocument>
   <relatedDocument typeCode="COMP">
      <expressionDocument>
         <id root="2c9280827eb12de9017f46ca852237f7"/>
         <text mediaType="text/cql">
            <reference value="https://emeasuretool.cms.gov/libraries/b2549666-62cd-4750-8e34-047a0451d042/PalliativeCareExclusionECQM-v2-0-000-QDM-5-6.cql"/>
            <translation mediaType="application/elm+xml">
               <reference value="https://emeasuretool.cms.gov/libraries/b2549666-62cd-4750-8e34-047a0451d042/PalliativeCareExclusionECQM-v2-0-000-QDM-5-6.xml"/>
            </translation>
            <translation mediaType="application/elm+json">
               <reference value="https://emeasuretool.cms.gov/libraries/b2549666-62cd-4750-8e34-047a0451d042/PalliativeCareExclusionECQM-v2-0-000-QDM-5-6.json"/>
            </translation>
         </text>
         <setId extension="b2549666-62cd-4750-8e34-047a0451d042"
                identifierName="PalliativeCareExclusionECQM"
                root="https://emeasuretool.cms.gov/libraries"/>
         <versionNumber value="2.0.000"/>
      </expressionDocument>
   </relatedDocument>
   <relatedDocument typeCode="COMP">
      <expressionDocument>
         <id root="2c9280827eb12de9017f46d2441c380e"/>
         <text mediaType="text/cql">
            <reference value="https://emeasuretool.cms.gov/libraries/60aebe4a-ef31-4ff1-8cfb-93bd7ee79cf5/AdvancedIllnessandFrailtyExclusionECQM-v7-0-000-QDM-5-6.cql"/>
            <translation mediaType="application/elm+xml">
               <reference value="https://emeasuretool.cms.gov/libraries/60aebe4a-ef31-4ff1-8cfb-93bd7ee79cf5/AdvancedIllnessandFrailtyExclusionECQM-v7-0-000-QDM-5-6.xml"/>
            </translation>
            <translation mediaType="application/elm+json">
               <reference value="https://emeasuretool.cms.gov/libraries/60aebe4a-ef31-4ff1-8cfb-93bd7ee79cf5/AdvancedIllnessandFrailtyExclusionECQM-v7-0-000-QDM-5-6.json"/>
            </translation>
         </text>
         <setId extension="60aebe4a-ef31-4ff1-8cfb-93bd7ee79cf5"
                identifierName="AdvancedIllnessandFrailtyExclusionECQM"
                root="https://emeasuretool.cms.gov/libraries"/>
         <versionNumber value="7.0.000"/>
      </expressionDocument>
   </relatedDocument>
   <relatedDocument typeCode="COMP">
      <expressionDocument>
         <id root="2c9280857b2aeb52017b5f8b96c31ff8"/>
         <text mediaType="text/cql">
            <reference value="https://emeasuretool.cms.gov/libraries/8bdc0a19-b210-4a58-8a07-f5d95a34eca9/MATGlobalCommonFunctions-v7-0-000-QDM-5-6.cql"/>
            <translation mediaType="application/elm+xml">
               <reference value="https://emeasuretool.cms.gov/libraries/8bdc0a19-b210-4a58-8a07-f5d95a34eca9/MATGlobalCommonFunctions-v7-0-000-QDM-5-6.xml"/>
            </translation>
            <translation mediaType="application/elm+json">
               <reference value="https://emeasuretool.cms.gov/libraries/8bdc0a19-b210-4a58-8a07-f5d95a34eca9/MATGlobalCommonFunctions-v7-0-000-QDM-5-6.json"/>
            </translation>
         </text>
         <setId extension="8bdc0a19-b210-4a58-8a07-f5d95a34eca9"
                identifierName="MATGlobalCommonFunctions"
                root="https://emeasuretool.cms.gov/libraries"/>
         <versionNumber value="7.0.000"/>
      </expressionDocument>
   </relatedDocument>
   <relatedDocument typeCode="COMP">
      <expressionDocument>
         <id root="2c9280827eb12de9017f46ba134b37d9"/>
         <text mediaType="text/cql">
            <reference value="https://emeasuretool.cms.gov/libraries/64299b80-f383-4dc9-82e4-d6ef0b271b11/Hospice-v4-0-000-QDM-5-6.cql"/>
            <translation mediaType="application/elm+xml">
               <reference value="https://emeasuretool.cms.gov/libraries/64299b80-f383-4dc9-82e4-d6ef0b271b11/Hospice-v4-0-000-QDM-5-6.xml"/>
            </translation>
            <translation mediaType="application/elm+json">
               <reference value="https://emeasuretool.cms.gov/libraries/64299b80-f383-4dc9-82e4-d6ef0b271b11/Hospice-v4-0-000-QDM-5-6.json"/>
            </translation>
         </text>
         <setId extension="64299b80-f383-4dc9-82e4-d6ef0b271b11" identifierName="Hospice"
                root="https://emeasuretool.cms.gov/libraries"/>
         <versionNumber value="4.0.000"/>
      </expressionDocument>
   </relatedDocument>
   <controlVariable>
      <measurePeriod>
         <id extension="measureperiod" root="13014c58-bb23-49b4-b005-121ff810c770"/>
         <code code="MSRTP" codeSystem="2.16.840.1.113883.5.4">
            <originalText value="Measurement Period"/>
         </code>
         <value xsi:type="PIVL_TS">
            <phase highClosed="true" lowClosed="true">
               <low value="20220101"/>
               <width unit="a" value="1" xsi:type="PQ"/>
            </phase>
            <period unit="a" value="1"/>
         </value>
      </measurePeriod>
   </controlVariable>
   <subjectOf>
      <measureAttribute>
         <code nullFlavor="OTH">
            <originalText value="eCQM Identifier (Measure Authoring Tool)"/>
         </code>
         <value mediaType="text/plain" value="122" xsi:type="ED"/>
      </measureAttribute>
   </subjectOf>
   <subjectOf>
      <measureAttribute>
         <code nullFlavor="OTH">
            <originalText value="NQF Number"/>
         </code>
         <value mediaType="text/plain" value="Not Applicable" xsi:type="ED"/>
      </measureAttribute>
   </subjectOf>
   <subjectOf>
      <measureAttribute>
         <code code="COPY" codeSystem="2.16.840.1.113883.5.4">
            <displayName value="Copyright"/>
         </code>
         <value mediaType="text/plain"
                value="This Physician Performance Measure (Measure) and related data specifications are owned and were developed by the National Committee for Quality Assurance (NCQA). NCQA is not responsible for any use of the Measure. NCQA makes no representations, warranties, or endorsement about the quality of any organization or physician that uses or reports performance measures and NCQA has no liability to anyone who relies on such measures or specifications. NCQA holds a copyright in the Measure. The Measure can be reproduced and distributed, without modification, for noncommercial purposes (e.g., use by healthcare providers in connection with their practices) without obtaining approval from NCQA. Commercial use is defined as the sale, licensing, or distribution of the Measure for commercial gain, or incorporation of the Measure into a product or service that is sold, licensed or distributed for commercial gain. All commercial uses or requests for modification must be approved by NCQA and are subject to a license at the discretion of NCQA. (C) 2012-2021 National Committee for Quality Assurance. All Rights Reserved.&#xA;&#xA;Limited proprietary coding is contained in the Measure specifications for user convenience. Users of proprietary code sets should obtain all necessary licenses from the owners of the code sets. NCQA disclaims all liability for use or accuracy of any third party codes contained in the specifications.&#xA;&#xA;CPT(R) contained in the Measure specifications is copyright 2004-2021 American Medical Association. LOINC(R) copyright 2004-2021 Regenstrief Institute, Inc. This material contains SNOMED Clinical Terms(R) (SNOMED CT[R]) copyright 2004-2021 International Health Terminology Standards Development Organisation. ICD-10 copyright 2021 World Health Organization. All Rights Reserved."
                xsi:type="ED"/>
      </measureAttribute>
   </subjectOf>
   <subjectOf>
      <measureAttribute>
         <code code="DISC" codeSystem="2.16.840.1.113883.5.4">
            <displayName value="Disclaimer"/>
         </code>
         <value mediaType="text/plain"
                value="The performance Measure is not a clinical guideline and does not establish a standard of medical care, and has not been tested for all potential applications. THE MEASURE AND SPECIFICATIONS ARE PROVIDED &quot;AS IS&quot; WITHOUT WARRANTY OF ANY KIND.&#xA; &#xA;Due to technical limitations, registered trademarks are indicated by (R) or [R] and unregistered trademarks are indicated by (TM) or [TM]."
                xsi:type="ED"/>
      </measureAttribute>
   </subjectOf>
   <subjectOf>
      <measureAttribute>
         <code code="MSRSCORE" codeSystem="2.16.840.1.113883.5.4">
            <displayName value="Measure Scoring"/>
         </code>
         <value code="PROPOR" codeSystem="2.16.840.1.113883.5.1063" xsi:type="CD">
            <displayName value="Proportion"/>
         </value>
      </measureAttribute>
   </subjectOf>
   <subjectOf>
      <measureAttribute>
         <code code="MSRTYPE" codeSystem="2.16.840.1.113883.5.4">
            <displayName value="Measure Type"/>
         </code>
         <value code="INTERM-OM" codeSystem="2.16.840.1.113883.5.1063" xsi:type="CD">
            <displayName value="INTERM-OM"/>
         </value>
      </measureAttribute>
   </subjectOf>
   <subjectOf>
      <measureAttribute>
         <code code="STRAT" codeSystem="2.16.840.1.113883.5.4">
            <displayName value="Stratification"/>
         </code>
         <value mediaType="text/plain" value="None" xsi:type="ED"/>
      </measureAttribute>
   </subjectOf>
   <subjectOf>
      <measureAttribute>
         <code code="MSRADJ" codeSystem="2.16.840.1.113883.5.4">
            <displayName value="Risk Adjustment"/>
         </code>
         <value mediaType="text/plain" value="None" xsi:type="ED"/>
      </measureAttribute>
   </subjectOf>
   <subjectOf>
      <measureAttribute>
         <code code="MSRAGG" codeSystem="2.16.840.1.113883.5.4">
            <displayName value="Rate Aggregation"/>
         </code>
         <value mediaType="text/plain" value="None" xsi:type="ED"/>
      </measureAttribute>
   </subjectOf>
   <subjectOf>
      <measureAttribute>
         <code code="RAT" codeSystem="2.16.840.1.113883.5.4">
            <displayName value="Rationale"/>
         </code>
         <value mediaType="text/plain"
                value="Diabetes is the seventh leading cause of death in the United States. In 2017, diabetes affected approximately 34 million Americans (10.5 percent of the U.S. population) and killed approximately 84,000 people (Centers for Disease Control and Prevention [CDC], 2020a). Diabetes is a long-lasting disease marked by high blood glucose levels, resulting from the body's inability to produce or use insulin properly (CDC, 2020b). People with diabetes are at increased risk of serious health complications including vision loss, heart disease, stroke, kidney damage, amputation of feet or legs, and premature death (CDC, 2021). &#xA;&#xA;In 2017, diabetes cost the U.S. an estimated $327 billion: $237 billion in direct medical costs and $90 billion in reduced productivity. This is a 34 percent increase from the estimated $245 billion spent on diabetes in 2012 (American Diabetes Association [ADA], 2018).  &#xA;&#xA;Controlling A1c blood levels helps reduce the risk of microvascular complications (eye, kidney and nerve diseases) (ADA, 2021)."
                xsi:type="ED"/>
      </measureAttribute>
   </subjectOf>
   <subjectOf>
      <measureAttribute>
         <code code="CRS" codeSystem="2.16.840.1.113883.5.4">
            <displayName value="Clinical Recommendation Statement"/>
         </code>
         <value mediaType="text/plain"
                value="American Diabetes Association (2021):&#xA;&#xA;- An A1C goal for many nonpregnant adults of &lt;7% (53 mmol/mol) without significant hypocalcemia is appropriate. (Level of evidence: A)&#xA;&#xA;- On the basis of provider judgement and patient preference, achievement of lower A1C levels than the goal of 7% may be acceptable, and even beneficial,  if it can be achieved safely without significant hypoglycemia or other adverse effects of treatment. (Level of evidence: C)&#xA;&#xA;- Less stringent A1C goals (such as &lt;8% [64 mmol/mol]) may be appropriate for patients with limited life expectancy, where the harms of treatment are greater than the benefits. (Level of evidence: B)"
                xsi:type="ED"/>
      </measureAttribute>
   </subjectOf>
   <subjectOf>
      <measureAttribute>
         <code code="IDUR" codeSystem="2.16.840.1.113883.5.4">
            <displayName value="Improvement Notation"/>
         </code>
         <value mediaType="text/plain" value="Lower score indicates better quality"
                xsi:type="ED"/>
      </measureAttribute>
   </subjectOf>
   <subjectOf>
      <measureAttribute>
         <code code="REF" codeSystem="2.16.840.1.113883.5.4">
            <displayName value="Reference"/>
         </code>
         <value mediaType="text/plain"
                value="CITATIONAmerican Diabetes Association. (2018). Economic Costs of Diabetes in the U.S. in 2017. Diabetes Care, 41, 917-928. Retrieved from http://care.diabetesjournals.org/content/early/2018/03/20/dci18-0007"
                xsi:type="ED"/>
      </measureAttribute>
   </subjectOf>
   <subjectOf>
      <measureAttribute>
         <code code="REF" codeSystem="2.16.840.1.113883.5.4">
            <displayName value="Reference"/>
         </code>
         <value mediaType="text/plain"
                value="CITATIONAmerican Diabetes Association. (2021). 6. Glycemic Targets: Standards of Medical Care in Diabetes–2021. Diabetes Care 2021; 44(Suppl. 1):S73–S84. https://doi.org/10.2337/dc21-S006"
                xsi:type="ED"/>
      </measureAttribute>
   </subjectOf>
   <subjectOf>
      <measureAttribute>
         <code code="REF" codeSystem="2.16.840.1.113883.5.4">
            <displayName value="Reference"/>
         </code>
         <value mediaType="text/plain"
                value="CITATIONCenters for Disease Control and Prevention. (2021). Diabetes Report Card 2019. Atlanta, GA: Centers for Disease Control and Prevention, US Dept of Health and Human Services. Retrieved from https://www.cdc.gov/diabetes/library/reports/reportcard.html"
                xsi:type="ED"/>
      </measureAttribute>
   </subjectOf>
   <subjectOf>
      <measureAttribute>
         <code code="REF" codeSystem="2.16.840.1.113883.5.4">
            <displayName value="Reference"/>
         </code>
         <value mediaType="text/plain"
                value="CITATIONCenters for Disease Control and Prevention. (2020a). National Diabetes Statistics Report, 2020. Atlanta, GA: Centers for Disease Control and Prevention, U.S. Dept of Health and Human Services. Retrieved from https://www.cdc.gov/diabetes/data/statistics-report/index.html"
                xsi:type="ED"/>
      </measureAttribute>
   </subjectOf>
   <subjectOf>
      <measureAttribute>
         <code code="REF" codeSystem="2.16.840.1.113883.5.4">
            <displayName value="Reference"/>
         </code>
         <value mediaType="text/plain"
                value="CITATIONCenters for Disease Control and Prevention. (2020b). Diabetes Basics. Retrieved from https://www.cdc.gov/diabetes/basics/diabetes.html"
                xsi:type="ED"/>
      </measureAttribute>
   </subjectOf>
   <subjectOf>
      <measureAttribute>
         <code code="DEF" codeSystem="2.16.840.1.113883.5.4">
            <displayName value="Definition"/>
         </code>
         <value mediaType="text/plain" value="None" xsi:type="ED"/>
      </measureAttribute>
   </subjectOf>
   <subjectOf>
      <measureAttribute>
         <code code="GUIDE" codeSystem="2.16.840.1.113883.5.4">
            <displayName value="Guidance"/>
         </code>
         <value mediaType="text/plain"
                value="If the HbA1c test result is in the medical record, the test can be used to determine numerator compliance.&#xA;&#xA;This eCQM is a patient-based measure.&#xA;&#xA;This version of the eCQM uses QDM version 5.6. Please refer to the eCQI resource center (https://ecqi.healthit.gov/qdm) for more information on the QDM."
                xsi:type="ED"/>
      </measureAttribute>
   </subjectOf>
   <subjectOf>
      <measureAttribute>
         <code code="TRANF" codeSystem="2.16.840.1.113883.5.4">
            <displayName value="Transmission Format"/>
         </code>
         <value mediaType="text/plain" value="TBD" xsi:type="ED"/>
      </measureAttribute>
   </subjectOf>
   <subjectOf>
      <measureAttribute>
         <code code="IPOP" codeSystem="2.16.840.1.113883.5.4">
            <displayName value="Initial Population"/>
         </code>
         <value mediaType="text/plain"
                value="Patients 18-75 years of age by the end of the measurement period, with diabetes with a visit during the measurement period"
                xsi:type="ED"/>
      </measureAttribute>
   </subjectOf>
   <subjectOf>
      <measureAttribute>
         <code code="DENOM" codeSystem="2.16.840.1.113883.5.4">
            <displayName value="Denominator"/>
         </code>
         <value mediaType="text/plain" value="Equals Initial Population" xsi:type="ED"/>
      </measureAttribute>
   </subjectOf>
   <subjectOf>
      <measureAttribute>
         <code code="DENEX" codeSystem="2.16.840.1.113883.5.4">
            <displayName value="Denominator Exclusions"/>
         </code>
         <value mediaType="text/plain"
                value="Exclude patients who are in hospice care for any part of the measurement period.&#xA;&#xA;Exclude patients 66 and older by the end of the measurement period who are living long term in a nursing home any time on or before the end of during the measurement period.&#xA;&#xA;Exclude patients 66 and older by the end of the measurement period with an indication of frailty for any part of the measurement period who also meet any of the following advanced illness criteria:&#xA;- Advanced illness with two outpatient encounters during the measurement period or the year prior&#xA;- OR advanced illness with one inpatient encounter during the measurement period or the year prior&#xA;- OR taking dementia medications during the measurement period or the year prior&#xA; &#xA;Exclude patients receiving palliative care for any part of the measurement period."
                xsi:type="ED"/>
      </measureAttribute>
   </subjectOf>
   <subjectOf>
      <measureAttribute>
         <code code="NUMER" codeSystem="2.16.840.1.113883.5.4">
            <displayName value="Numerator"/>
         </code>
         <value mediaType="text/plain"
                value="Patients whose most recent HbA1c level (performed during the measurement period) is &gt;9.0% or is missing, or was not performed during the measurement period"
                xsi:type="ED"/>
      </measureAttribute>
   </subjectOf>
   <subjectOf>
      <measureAttribute>
         <code code="NUMEX" codeSystem="2.16.840.1.113883.5.4">
            <displayName value="Numerator Exclusions"/>
         </code>
         <value mediaType="text/plain" value="Not Applicable" xsi:type="ED"/>
      </measureAttribute>
   </subjectOf>
   <subjectOf>
      <measureAttribute>
         <code code="DENEXCEP" codeSystem="2.16.840.1.113883.5.4">
            <displayName value="Denominator Exceptions"/>
         </code>
         <value mediaType="text/plain" value="None" xsi:type="ED"/>
      </measureAttribute>
   </subjectOf>
   <subjectOf>
      <measureAttribute>
         <code code="SDE" codeSystem="2.16.840.1.113883.5.4">
            <displayName value="Supplemental Data Elements"/>
         </code>
         <value mediaType="text/plain"
                value="For every patient evaluated by this measure also identify payer, race, ethnicity and sex"
                xsi:type="ED"/>
      </measureAttribute>
   </subjectOf>
   <componentOf>
      <qualityMeasureSet classCode="ACT">
         <id root="f2986519-5a4e-4149-a8f2-af0a1dc7f6bc"/>
         <title value="None"/>
      </qualityMeasureSet>
   </componentOf>
   <!--Data Criteria Section-->
   <component>
      <dataCriteriaSection>
         <templateId>
            <item extension="2021-02-01" root="2.16.840.1.113883.10.20.28.2.6"/>
         </templateId>
         <code code="57025-9" codeSystem="2.16.840.1.113883.6.1"/>
         <title value="Data Criteria Section"/>
         <text/>
         <entry typeCode="DRIV">
            <localVariableName value="ONCAdministrativeSex_PatientCharacteristicSex_IWN3M"/>
            <observationCriteria classCode="OBS" moodCode="EVN">
               <templateId>
                  <item extension="2017-05-01" root="2.16.840.1.113883.10.20.28.4.55"/>
               </templateId>
               <id extension="ONCAdministrativeSex_PatientCharacteristicSex"
                   root="83aa6e89-146d-4432-8101-72c1b74df5f5"/>
               <code code="263495000" codeSystem="2.16.840.1.113883.6.96" codeSystemName="SNOMED CT">
                  <displayName value="Gender"/>
               </code>
               <title value="Patient Characteristic Sex"/>
               <statusCode code="COMPLETED"/>
               <value valueSet="2.16.840.1.113762.1.4.1" xsi:type="CD"/>
            </observationCriteria>
         </entry>
         <entry typeCode="DRIV">
            <localVariableName value="TelephoneVisits_EncounterPerformed_xioiv"/>
            <encounterCriteria classCode="ENC" moodCode="EVN">
               <templateId>
                  <item extension="2021-02-01" root="2.16.840.1.113883.10.20.28.4.5"/>
               </templateId>
               <id extension="TelephoneVisits_EncounterPerformed"
                   root="b1440521-22e2-4a67-ae79-13d65ba68b94"/>
               <code valueSet="2.16.840.1.113883.3.464.1003.101.12.1080"/>
               <title value="Encounter, Performed"/>
               <statusCode code="COMPLETED"/>
            </encounterCriteria>
         </entry>
         <entry typeCode="DRIV">
            <localVariableName value="NutritionServices_EncounterPerformed_oOZRa"/>
            <encounterCriteria classCode="ENC" moodCode="EVN">
               <templateId>
                  <item extension="2021-02-01" root="2.16.840.1.113883.10.20.28.4.5"/>
               </templateId>
               <id extension="NutritionServices_EncounterPerformed"
                   root="02775b77-cf36-4c63-b81f-5c26f0144efa"/>
               <code valueSet="2.16.840.1.113883.3.464.1003.1006"/>
               <title value="Encounter, Performed"/>
               <statusCode code="COMPLETED"/>
            </encounterCriteria>
         </entry>
         <entry typeCode="DRIV">
            <localVariableName value="AcuteInpatient_EncounterPerformed_BcZzD"/>
            <encounterCriteria classCode="ENC" moodCode="EVN">
               <templateId>
                  <item extension="2021-02-01" root="2.16.840.1.113883.10.20.28.4.5"/>
               </templateId>
               <id extension="AcuteInpatient_EncounterPerformed"
                   root="0c42fbd2-5784-4eeb-8c3f-dad620b76bd5"/>
               <code valueSet="2.16.840.1.113883.3.464.1003.101.12.1083"/>
               <title value="Encounter, Performed"/>
               <statusCode code="COMPLETED"/>
            </encounterCriteria>
         </entry>
         <entry typeCode="DRIV">
            <localVariableName value="EncounterInpatient_EncounterPerformed_A6koM"/>
            <encounterCriteria classCode="ENC" moodCode="EVN">
               <templateId>
                  <item extension="2021-02-01" root="2.16.840.1.113883.10.20.28.4.5"/>
               </templateId>
               <id extension="EncounterInpatient_EncounterPerformed"
                   root="59c3933e-c568-4119-b89d-c29b7c752ef3"/>
               <code valueSet="2.16.840.1.113883.3.666.5.307"/>
               <title value="Encounter, Performed"/>
               <statusCode code="COMPLETED"/>
            </encounterCriteria>
         </entry>
         <entry typeCode="DRIV">
            <localVariableName value="HospiceCareAmbulatory_InterventionOrder_4lTFb"/>
            <actCriteria classCode="ACT" moodCode="RQO">
               <templateId>
                  <item extension="2021-02-01" root="2.16.840.1.113883.10.20.28.4.35"/>
               </templateId>
               <id extension="HospiceCareAmbulatory_InterventionOrder"
                   root="1a2e5eaf-2061-42da-a70b-5906364289a2"/>
               <code valueSet="2.16.840.1.113883.3.526.3.1584"/>
               <title value="Intervention, Order"/>
               <statusCode code="ACTIVE"/>
            </actCriteria>
         </entry>
         <entry typeCode="DRIV">
            <localVariableName value="HospiceCareAmbulatory_InterventionPerformed_8jx6j"/>
            <actCriteria classCode="ACT" moodCode="EVN">
               <templateId>
                  <item extension="2021-02-01" root="2.16.840.1.113883.10.20.28.4.36"/>
               </templateId>
               <id extension="HospiceCareAmbulatory_InterventionPerformed"
                   root="1a2e5eaf-2061-42da-a70b-5906364289a2"/>
               <code valueSet="2.16.840.1.113883.3.526.3.1584"/>
               <title value="Intervention, Performed"/>
               <statusCode code="COMPLETED"/>
            </actCriteria>
         </entry>
         <entry typeCode="DRIV">
            <localVariableName value="FrailtyDevice_DeviceOrder_MQsMh"/>
            <supplyCriteria classCode="SPLY" moodCode="RQO">
               <templateId>
                  <item extension="2021-02-01" root="2.16.840.1.113883.10.20.28.4.15"/>
               </templateId>
               <id extension="FrailtyDevice_DeviceOrder"
                   root="09d12239-3f43-47e8-9d01-84e20943e503"/>
               <title value="Device, Order"/>
               <statusCode code="ACTIVE"/>
			            <participation typeCode="DEV">
                  <role classCode="MANU">
                     <playingDevice classCode="DEV" determinerCode="KIND">
                        <code valueSet="2.16.840.1.113883.3.464.1003.118.12.1300"/>
                     </playingDevice>
                  </role>
               </participation>
		          </supplyCriteria>
         </entry>
         <entry typeCode="DRIV">
            <localVariableName value="FrailtyEncounter_EncounterPerformed_uPQtz"/>
            <encounterCriteria classCode="ENC" moodCode="EVN">
               <templateId>
                  <item extension="2021-02-01" root="2.16.840.1.113883.10.20.28.4.5"/>
               </templateId>
               <id extension="FrailtyEncounter_EncounterPerformed"
                   root="f49a4332-bb2f-4685-8788-3946d624776e"/>
               <code valueSet="2.16.840.1.113883.3.464.1003.101.12.1088"/>
               <title value="Encounter, Performed"/>
               <statusCode code="COMPLETED"/>
            </encounterCriteria>
         </entry>
         <entry typeCode="DRIV">
            <localVariableName value="HbA1cLaboratoryTest_LaboratoryTestPerformed_VSU1A"/>
            <observationCriteria classCode="OBS" moodCode="EVN">
               <templateId>
                  <item extension="2021-02-01" root="2.16.840.1.113883.10.20.28.4.42"/>
               </templateId>
               <id extension="HbA1cLaboratoryTest_LaboratoryTestPerformed"
                   root="3b63e1f8-aaf3-4b56-9869-eb05ccc33687"/>
               <code valueSet="2.16.840.1.113883.3.464.1003.198.12.1013"/>
               <title value="Laboratory Test, Performed"/>
               <statusCode code="COMPLETED"/>
            </observationCriteria>
         </entry>
         <entry typeCode="DRIV">
            <localVariableName value="PreventiveCareServicesEstablishedOfficeVisit18andUp_EncounterPerformed_YDLRf"/>
            <encounterCriteria classCode="ENC" moodCode="EVN">
               <templateId>
                  <item extension="2021-02-01" root="2.16.840.1.113883.10.20.28.4.5"/>
               </templateId>
               <id extension="PreventiveCareServicesEstablishedOfficeVisit18andUp_EncounterPerformed"
                   root="40280381-3d61-56a7-013e-62240570257e"/>
               <code valueSet="2.16.840.1.113883.3.464.1003.101.12.1025"/>
               <title value="Encounter, Performed"/>
               <statusCode code="COMPLETED"/>
            </encounterCriteria>
         </entry>
         <entry typeCode="DRIV">
            <localVariableName value="FrailtyDiagnosis_Diagnosis_lvDe3"/>
            <observationCriteria classCode="OBS" moodCode="EVN">
               <templateId>
                  <item extension="2021-02-01" root="2.16.840.1.113883.10.20.28.4.110"/>
               </templateId>
               <id extension="FrailtyDiagnosis_Diagnosis"
                   root="ffe64f65-5595-4ccc-8663-935a1017f45b"/>
               <code code="282291009" codeSystem="2.16.840.1.113883.6.96" codeSystemName="SNOMED CT">
                  <displayName value="Diagnosis"/>
               </code>
               <title value="Diagnosis"/>
               <statusCode code="COMPLETED"/>
               <value valueSet="2.16.840.1.113883.3.464.1003.113.12.1074" xsi:type="CD"/>
            </observationCriteria>
         </entry>
         <entry typeCode="DRIV">
            <localVariableName value="HomeHealthcareServices_EncounterPerformed_ptLiF"/>
            <encounterCriteria classCode="ENC" moodCode="EVN">
               <templateId>
                  <item extension="2021-02-01" root="2.16.840.1.113883.10.20.28.4.5"/>
               </templateId>
               <id extension="HomeHealthcareServices_EncounterPerformed"
                   root="40280381-3d61-56a7-013e-622405702580"/>
               <code valueSet="2.16.840.1.113883.3.464.1003.101.12.1016"/>
               <title value="Encounter, Performed"/>
               <statusCode code="COMPLETED"/>
            </encounterCriteria>
         </entry>
         <entry typeCode="DRIV">
            <localVariableName value="Race_PatientCharacteristicRace_ioYek"/>
            <observationCriteria classCode="OBS" moodCode="EVN">
               <templateId>
                  <item extension="2017-05-01" root="2.16.840.1.113883.10.20.28.4.59"/>
               </templateId>
               <id extension="Race_PatientCharacteristicRace"
                   root="c3a4bf0c-b283-42c0-8990-29a971f9eb4d"/>
               <code code="32624-9" codeSystem="2.16.840.1.113883.6.1" codeSystemName="LOINC">
                  <displayName value="Race"/>
               </code>
               <title value="Patient Characteristic Race"/>
               <statusCode code="COMPLETED"/>
               <value valueSet="2.16.840.1.114222.4.11.836" xsi:type="CD"/>
            </observationCriteria>
         </entry>
         <entry typeCode="DRIV">
            <localVariableName value="OfficeVisit_EncounterPerformed_FIJ6Q"/>
            <encounterCriteria classCode="ENC" moodCode="EVN">
               <templateId>
                  <item extension="2021-02-01" root="2.16.840.1.113883.10.20.28.4.5"/>
               </templateId>
               <id extension="OfficeVisit_EncounterPerformed"
                   root="40280381-3d61-56a7-013e-62240570257c"/>
               <code valueSet="2.16.840.1.113883.3.464.1003.101.12.1001"/>
               <title value="Encounter, Performed"/>
               <statusCode code="COMPLETED"/>
            </encounterCriteria>
         </entry>
         <entry typeCode="DRIV">
            <localVariableName value="Payer_PatientCharacteristicPayer_TMsqa"/>
            <observationCriteria classCode="OBS" moodCode="EVN">
               <templateId>
                  <item extension="2017-05-01" root="2.16.840.1.113883.10.20.28.4.58"/>
               </templateId>
               <id extension="Payer_PatientCharacteristicPayer"
                   root="64692662-357c-46ce-940c-825503b6aea6"/>
               <code code="48768-6" codeSystem="2.16.840.1.113883.6.1" codeSystemName="LOINC">
                  <displayName value="Payer"/>
               </code>
               <title value="Patient Characteristic Payer"/>
               <statusCode code="COMPLETED"/>
               <value valueSet="2.16.840.1.114222.4.11.3591" xsi:type="CD"/>
            </observationCriteria>
         </entry>
         <entry typeCode="DRIV">
            <localVariableName value="NonacuteInpatient_EncounterPerformed_zd8K6"/>
            <encounterCriteria classCode="ENC" moodCode="EVN">
               <templateId>
                  <item extension="2021-02-01" root="2.16.840.1.113883.10.20.28.4.5"/>
               </templateId>
               <id extension="NonacuteInpatient_EncounterPerformed"
                   root="091d1af8-71ce-42be-a29d-341c25b64454"/>
               <code valueSet="2.16.840.1.113883.3.464.1003.101.12.1084"/>
               <title value="Encounter, Performed"/>
               <statusCode code="COMPLETED"/>
            </encounterCriteria>
         </entry>
         <entry typeCode="DRIV">
            <localVariableName value="DementiaMedications_MedicationActive_R9Z6m"/>
            <substanceAdministrationCriteria classCode="SBADM" moodCode="EVN">
               <templateId>
                  <item extension="2021-02-01" root="2.16.840.1.113883.10.20.28.4.44"/>
               </templateId>
               <id extension="DementiaMedications_MedicationActive"
                   root="8d5f9441-8c89-47a0-86ec-f41fdca53424"/>
               <title value="Medication, Active"/>
               <statusCode code="ACTIVE"/>
			            <participation typeCode="CSM">
                  <role classCode="MANU">
                     <playingMaterial classCode="MMAT" determinerCode="KIND">
                        <code valueSet="2.16.840.1.113883.3.464.1003.196.12.1510"/>
                     </playingMaterial>
                  </role>
               </participation>
		          </substanceAdministrationCriteria>
         </entry>
         <entry typeCode="DRIV">
            <localVariableName value="PalliativeCareIntervention_InterventionPerformed_K9ilh"/>
            <actCriteria classCode="ACT" moodCode="EVN">
               <templateId>
                  <item extension="2021-02-01" root="2.16.840.1.113883.10.20.28.4.36"/>
               </templateId>
               <id extension="PalliativeCareIntervention_InterventionPerformed"
                   root="4c1c7283-05bd-4b45-b59e-9cc76b294159"/>
               <code valueSet="2.16.840.1.113883.3.464.1003.198.12.1135"/>
               <title value="Intervention, Performed"/>
               <statusCode code="COMPLETED"/>
            </actCriteria>
         </entry>
         <entry typeCode="DRIV">
            <localVariableName value="PalliativeCareEncounter_EncounterPerformed_dN35o"/>
            <encounterCriteria classCode="ENC" moodCode="EVN">
               <templateId>
                  <item extension="2021-02-01" root="2.16.840.1.113883.10.20.28.4.5"/>
               </templateId>
               <id extension="PalliativeCareEncounter_EncounterPerformed"
                   root="7d662797-a810-4f66-9362-c419d038be97"/>
               <code valueSet="2.16.840.1.113883.3.464.1003.101.12.1090"/>
               <title value="Encounter, Performed"/>
               <statusCode code="COMPLETED"/>
            </encounterCriteria>
         </entry>
         <entry typeCode="DRIV">
            <localVariableName value="FrailtySymptom_Symptom_IVJH1"/>
            <observationCriteria classCode="OBS" moodCode="EVN">
               <templateId>
                  <item extension="2021-02-01" root="2.16.840.1.113883.10.20.28.4.116"/>
               </templateId>
               <id extension="FrailtySymptom_Symptom" root="bfcb65b5-61f2-49b8-a2e9-f648e6a818c0"/>
               <code code="418799008" codeSystem="2.16.840.1.113883.6.96" codeSystemName="SNOMED CT">
                  <displayName value="Symptom"/>
               </code>
               <title value="Symptom"/>
               <statusCode code="COMPLETED"/>
               <value valueSet="2.16.840.1.113883.3.464.1003.113.12.1075" xsi:type="CD"/>
            </observationCriteria>
         </entry>
         <entry typeCode="DRIV">
            <localVariableName value="Observation_EncounterPerformed_QB8qD"/>
            <encounterCriteria classCode="ENC" moodCode="EVN">
               <templateId>
                  <item extension="2021-02-01" root="2.16.840.1.113883.10.20.28.4.5"/>
               </templateId>
               <id extension="Observation_EncounterPerformed"
                   root="65b06ccd-427f-499f-b5bf-aa9f350d0ca7"/>
               <code valueSet="2.16.840.1.113883.3.464.1003.101.12.1086"/>
               <title value="Encounter, Performed"/>
               <statusCode code="COMPLETED"/>
            </encounterCriteria>
         </entry>
         <entry typeCode="DRIV">
            <localVariableName value="AnnualWellnessVisit_EncounterPerformed_e0IDY"/>
            <encounterCriteria classCode="ENC" moodCode="EVN">
               <templateId>
                  <item extension="2021-02-01" root="2.16.840.1.113883.10.20.28.4.5"/>
               </templateId>
               <id extension="AnnualWellnessVisit_EncounterPerformed"
                   root="40280381-3d61-56a7-013e-622405712581"/>
               <code valueSet="2.16.840.1.113883.3.526.3.1240"/>
               <title value="Encounter, Performed"/>
               <statusCode code="COMPLETED"/>
            </encounterCriteria>
         </entry>
         <entry typeCode="DRIV">
            <localVariableName value="Outpatient_EncounterPerformed_HAOHJ"/>
            <encounterCriteria classCode="ENC" moodCode="EVN">
               <templateId>
                  <item extension="2021-02-01" root="2.16.840.1.113883.10.20.28.4.5"/>
               </templateId>
               <id extension="Outpatient_EncounterPerformed"
                   root="74132a0d-4844-43d8-a380-72d24f8efe6e"/>
               <code valueSet="2.16.840.1.113883.3.464.1003.101.12.1087"/>
               <title value="Encounter, Performed"/>
               <statusCode code="COMPLETED"/>
            </encounterCriteria>
         </entry>
         <entry typeCode="DRIV">
            <localVariableName value="Ethnicity_PatientCharacteristicEthnicity_cvby0"/>
            <observationCriteria classCode="OBS" moodCode="EVN">
               <templateId>
                  <item extension="2017-05-01" root="2.16.840.1.113883.10.20.28.4.56"/>
               </templateId>
               <id extension="Ethnicity_PatientCharacteristicEthnicity"
                   root="c8ba78cf-40f6-4093-862d-6006cc65023f"/>
               <code code="54133-4" codeSystem="2.16.840.1.113883.6.1" codeSystemName="LOINC">
                  <displayName value="Ethnicity"/>
               </code>
               <title value="Patient Characteristic Ethnicity"/>
               <statusCode code="COMPLETED"/>
               <value valueSet="2.16.840.1.114222.4.11.837" xsi:type="CD"/>
            </observationCriteria>
         </entry>
         <entry typeCode="DRIV">
            <localVariableName value="EmergencyDepartmentVisit_EncounterPerformed_s5GDn"/>
            <encounterCriteria classCode="ENC" moodCode="EVN">
               <templateId>
                  <item extension="2021-02-01" root="2.16.840.1.113883.10.20.28.4.5"/>
               </templateId>
               <id extension="EmergencyDepartmentVisit_EncounterPerformed"
                   root="d88b1e95-2e2e-4bfa-a4d6-286b09fade6e"/>
               <code valueSet="2.16.840.1.113883.3.464.1003.101.12.1010"/>
               <title value="Encounter, Performed"/>
               <statusCode code="COMPLETED"/>
            </encounterCriteria>
         </entry>
         <entry typeCode="DRIV">
            <localVariableName value="PreventiveCareServicesInitialOfficeVisit18andUp_EncounterPerformed_wm5tb"/>
            <encounterCriteria classCode="ENC" moodCode="EVN">
               <templateId>
                  <item extension="2021-02-01" root="2.16.840.1.113883.10.20.28.4.5"/>
               </templateId>
               <id extension="PreventiveCareServicesInitialOfficeVisit18andUp_EncounterPerformed"
                   root="40280381-3d61-56a7-013e-62240570257f"/>
               <code valueSet="2.16.840.1.113883.3.464.1003.101.12.1023"/>
               <title value="Encounter, Performed"/>
               <statusCode code="COMPLETED"/>
            </encounterCriteria>
         </entry>
         <entry typeCode="DRIV">
            <localVariableName value="HospiceEncounter_EncounterPerformed_9IigM"/>
            <encounterCriteria classCode="ENC" moodCode="EVN">
               <templateId>
                  <item extension="2021-02-01" root="2.16.840.1.113883.10.20.28.4.5"/>
               </templateId>
               <id extension="HospiceEncounter_EncounterPerformed"
                   root="93a22f5a-a867-4e89-bb6d-f087930fc43b"/>
               <code valueSet="2.16.840.1.113883.3.464.1003.1003"/>
               <title value="Encounter, Performed"/>
               <statusCode code="COMPLETED"/>
            </encounterCriteria>
         </entry>
         <entry typeCode="DRIV">
            <localVariableName value="Diabetes_Diagnosis_qEe48"/>
            <observationCriteria classCode="OBS" moodCode="EVN">
               <templateId>
                  <item extension="2021-02-01" root="2.16.840.1.113883.10.20.28.4.110"/>
               </templateId>
               <id extension="Diabetes_Diagnosis" root="dbaa8edd-2495-49f1-9d8d-86c97c3dd2da"/>
               <code code="282291009" codeSystem="2.16.840.1.113883.6.96" codeSystemName="SNOMED CT">
                  <displayName value="Diagnosis"/>
               </code>
               <title value="Diagnosis"/>
               <statusCode code="COMPLETED"/>
               <value valueSet="2.16.840.1.113883.3.464.1003.103.12.1001" xsi:type="CD"/>
            </observationCriteria>
         </entry>
         <entry typeCode="DRIV">
            <observationCriteria classCode="OBS" moodCode="EVN">
               <templateId>
                  <item extension="2021-02-01" root="2.16.840.1.113883.10.20.28.4.110"/>
               </templateId>
               <id extension="Z51.5_Diagnosis" root="37158985-6C00-407A-8E2D-A4875690C55F"/>
               <code code="282291009" codeSystem="2.16.840.1.113883.6.96" codeSystemName="SNOMED CT">
                  <displayName value="Diagnosis"/>
               </code>
               <title value="Diagnosis"/>
               <statusCode code="COMPLETED"/>
               <value code="Z51.5" codeSystem="2.16.840.1.113883.6.90" codeSystemName="ICD10CM"
                      xsi:type="CD"/>
            </observationCriteria>
         </entry>
         <entry typeCode="DRIV">
            <encounterCriteria classCode="ENC" moodCode="EVN">
               <templateId>
                  <item extension="2021-02-01" root="2.16.840.1.113883.10.20.28.4.5"/>
               </templateId>
               <id extension="97802_EncounterPerformed"
                   root="BDA8BE56-C5DA-47EA-B667-377BE7FF2B33"/>
               <code code="97802" codeSystem="2.16.840.1.113883.6.12" codeSystemName="CPT"/>
               <title value="Encounter, Performed"/>
               <statusCode code="COMPLETED"/>
            </encounterCriteria>
         </entry>
         <entry typeCode="DRIV">
            <encounterCriteria classCode="ENC" moodCode="EVN">
               <templateId>
                  <item extension="2021-02-01" root="2.16.840.1.113883.10.20.28.4.5"/>
               </templateId>
               <id extension="97803_EncounterPerformed"
                   root="148E5CD9-ED20-4023-B5DA-2AD182ACD37A"/>
               <code code="97803" codeSystem="2.16.840.1.113883.6.12" codeSystemName="CPT"/>
               <title value="Encounter, Performed"/>
               <statusCode code="COMPLETED"/>
            </encounterCriteria>
         </entry>
         <entry typeCode="DRIV">
            <encounterCriteria classCode="ENC" moodCode="EVN">
               <templateId>
                  <item extension="2021-02-01" root="2.16.840.1.113883.10.20.28.4.5"/>
               </templateId>
               <id extension="G0270_EncounterPerformed"
                   root="35CCD8BC-DE77-4297-9886-1D65E34B7521"/>
               <code code="G0270" codeSystem="2.16.840.1.113883.6.285" codeSystemName="HCPCS"/>
               <title value="Encounter, Performed"/>
               <statusCode code="COMPLETED"/>
            </encounterCriteria>
         </entry>
         <entry typeCode="DRIV">
            <observationCriteria classCode="OBS" moodCode="EVN">
               <templateId>
                  <item extension="2021-02-01" root="2.16.840.1.113883.10.20.28.4.117"/>
               </templateId>
               <id extension="71007-9_AssessmentPerformed"
                   root="E58D2956-3C5C-45CD-A077-9D15E6EDB6FD"/>
               <code code="71007-9" codeSystem="2.16.840.1.113883.6.1" codeSystemName="LOINC"/>
               <title value="Assessment, Performed"/>
               <statusCode code="COMPLETED"/>
            </observationCriteria>
         </entry>
         <entry typeCode="DRIV">
            <encounterCriteria classCode="ENC" moodCode="EVN">
               <templateId>
                  <item extension="2021-02-01" root="2.16.840.1.113883.10.20.28.4.5"/>
               </templateId>
               <id extension="G0271_EncounterPerformed"
                   root="E78C432B-91C3-4465-86CF-6783A3A096F1"/>
               <code code="G0271" codeSystem="2.16.840.1.113883.6.285" codeSystemName="HCPCS"/>
               <title value="Encounter, Performed"/>
               <statusCode code="COMPLETED"/>
            </encounterCriteria>
         </entry>
         <entry typeCode="DRIV">
            <observationCriteria classCode="OBS" moodCode="EVN">
               <templateId>
                  <item extension="2021-02-01" root="2.16.840.1.113883.10.20.28.4.117"/>
               </templateId>
               <id extension="98181-1_AssessmentPerformed"
                   root="42E22743-A5D9-451D-A029-2890D9326F47"/>
               <code code="98181-1" codeSystem="2.16.840.1.113883.6.1" codeSystemName="LOINC"/>
               <title value="Assessment, Performed"/>
               <statusCode code="COMPLETED"/>
            </observationCriteria>
         </entry>
         <entry typeCode="DRIV">
            <observationCriteria classCode="OBS" moodCode="EVN">
               <templateId>
                  <item extension="2021-02-01" root="2.16.840.1.113883.10.20.28.4.117"/>
               </templateId>
               <id extension="71802-3_AssessmentPerformed"
                   root="6517AF39-F810-49E1-A86A-C686FEA7D404"/>
               <code code="71802-3" codeSystem="2.16.840.1.113883.6.1" codeSystemName="LOINC"/>
               <title value="Assessment, Performed"/>
               <statusCode code="COMPLETED"/>
            </observationCriteria>
         </entry>
         <entry typeCode="DRIV">
            <observationCriteria classCode="OBS" moodCode="EVN">
               <templateId>
                  <item extension="2021-02-01" root="2.16.840.1.113883.10.20.28.4.117"/>
               </templateId>
               <id extension="45755-6_AssessmentPerformed"
                   root="2E6CB9A3-5D05-4CB2-8622-CFD881E9C7AF"/>
               <code code="45755-6" codeSystem="2.16.840.1.113883.6.1" codeSystemName="LOINC"/>
               <title value="Assessment, Performed"/>
               <statusCode code="COMPLETED"/>
            </observationCriteria>
         </entry>
         <entry typeCode="DRIV">
            <encounterCriteria classCode="ENC" moodCode="EVN">
               <templateId>
                  <item extension="2021-02-01" root="2.16.840.1.113883.10.20.28.4.5"/>
               </templateId>
               <id extension="97804_EncounterPerformed"
                   root="898E73BB-BF9B-4745-94D3-8AC24DD85281"/>
               <code code="97804" codeSystem="2.16.840.1.113883.6.12" codeSystemName="CPT"/>
               <title value="Encounter, Performed"/>
               <statusCode code="COMPLETED"/>
            </encounterCriteria>
         </entry>
      </dataCriteriaSection>
   </component>
   <component>
      <populationCriteriaSection>
         <templateId>
            <item extension="2017-08-01" root="2.16.840.1.113883.10.20.28.2.7"/>
         </templateId>
         <id extension="PopulationCriteria1" root="E169727D-89B8-4E33-821A-6475C94F86DB"/>
         <code code="57026-7" codeSystem="2.16.840.1.113883.6.1"/>
         <title value="Population Criteria Section"/>
         <text/>
         <component typeCode="COMP">
            <initialPopulationCriteria classCode="OBS" moodCode="EVN">
               <id extension="initialPopulation" root="03D10A51-45B8-4910-998B-7AA0E9B5B9C8"/>
               <code code="IPOP" codeSystem="2.16.840.1.113883.5.4" codeSystemName="Act Code"/>
               <precondition typeCode="PRCN">
                  <criteriaReference classCode="OBS" moodCode="EVN">
                     <id extension="DiabetesHemoglobinA1cHbA1cPoorControl9.&quot;Initial Population&quot;"
                         root="EFFB0CFA-05AF-4905-A84B-CAFBA22EE258"/>
                  </criteriaReference>
               </precondition>
            </initialPopulationCriteria>
         </component>
         <component typeCode="COMP">
            <denominatorCriteria classCode="OBS" moodCode="EVN">
               <id extension="denominator" root="04DFCA04-73BE-4D53-B178-A978A59FC516"/>
               <code code="DENOM" codeSystem="2.16.840.1.113883.5.4" codeSystemName="Act Code"/>
               <precondition typeCode="PRCN">
                  <criteriaReference classCode="OBS" moodCode="EVN">
                     <id extension="DiabetesHemoglobinA1cHbA1cPoorControl9.&quot;Denominator&quot;"
                         root="EFFB0CFA-05AF-4905-A84B-CAFBA22EE258"/>
                  </criteriaReference>
               </precondition>
            </denominatorCriteria>
         </component>
         <component typeCode="COMP">
            <denominatorExclusionCriteria classCode="OBS" moodCode="EVN">
               <id extension="denominatorExclusions" root="E12607B8-2F74-4528-9A0D-EBC9AA6392F8"/>
               <code code="DENEX" codeSystem="2.16.840.1.113883.5.4" codeSystemName="Act Code"/>
               <precondition typeCode="PRCN">
                  <criteriaReference classCode="OBS" moodCode="EVN">
                     <id extension="DiabetesHemoglobinA1cHbA1cPoorControl9.&quot;Denominator Exclusions&quot;"
                         root="EFFB0CFA-05AF-4905-A84B-CAFBA22EE258"/>
                  </criteriaReference>
               </precondition>
            </denominatorExclusionCriteria>
         </component>
         <component typeCode="COMP">
            <numeratorCriteria classCode="OBS" moodCode="EVN">
               <id extension="numerator" root="8EDDEC39-361E-41C4-89C0-5223A25F24C6"/>
               <code code="NUMER" codeSystem="2.16.840.1.113883.5.4" codeSystemName="Act Code"/>
               <precondition typeCode="PRCN">
                  <criteriaReference classCode="OBS" moodCode="EVN">
                     <id extension="DiabetesHemoglobinA1cHbA1cPoorControl9.&quot;Numerator&quot;"
                         root="EFFB0CFA-05AF-4905-A84B-CAFBA22EE258"/>
                  </criteriaReference>
               </precondition>
            </numeratorCriteria>
         </component>
         <component typeCode="COMP">
            <cql-ext:supplementalDataElement>
               <id extension="Supplemental Data Elements"
                   root="DB8681CA-9111-420C-9C92-A81F529A4531"/>
               <code code="SDE" codeSystem="2.16.840.1.113883.5.4" codeSystemName="Act Code"/>
               <precondition typeCode="PRCN">
                  <criteriaReference classCode="OBS" moodCode="EVN">
                     <id extension="DiabetesHemoglobinA1cHbA1cPoorControl9.&quot;SDE Ethnicity&quot;"
                         root="EFFB0CFA-05AF-4905-A84B-CAFBA22EE258"/>
                  </criteriaReference>
               </precondition>
            </cql-ext:supplementalDataElement>
         </component>
         <component typeCode="COMP">
            <cql-ext:supplementalDataElement>
               <id extension="Supplemental Data Elements"
                   root="B827461B-8815-44D6-A76E-C66F27DE3B31"/>
               <code code="SDE" codeSystem="2.16.840.1.113883.5.4" codeSystemName="Act Code"/>
               <precondition typeCode="PRCN">
                  <criteriaReference classCode="OBS" moodCode="EVN">
                     <id extension="DiabetesHemoglobinA1cHbA1cPoorControl9.&quot;SDE Payer&quot;"
                         root="EFFB0CFA-05AF-4905-A84B-CAFBA22EE258"/>
                  </criteriaReference>
               </precondition>
            </cql-ext:supplementalDataElement>
         </component>
         <component typeCode="COMP">
            <cql-ext:supplementalDataElement>
               <id extension="Supplemental Data Elements"
                   root="1D8CDAF8-AD55-4BB5-859D-AD38A56FB74A"/>
               <code code="SDE" codeSystem="2.16.840.1.113883.5.4" codeSystemName="Act Code"/>
               <precondition typeCode="PRCN">
                  <criteriaReference classCode="OBS" moodCode="EVN">
                     <id extension="DiabetesHemoglobinA1cHbA1cPoorControl9.&quot;SDE Race&quot;"
                         root="EFFB0CFA-05AF-4905-A84B-CAFBA22EE258"/>
                  </criteriaReference>
               </precondition>
            </cql-ext:supplementalDataElement>
         </component>
         <component typeCode="COMP">
            <cql-ext:supplementalDataElement>
               <id extension="Supplemental Data Elements"
                   root="37851C6D-3B18-4DFC-AEEB-D87CF2E7E69A"/>
               <code code="SDE" codeSystem="2.16.840.1.113883.5.4" codeSystemName="Act Code"/>
               <precondition typeCode="PRCN">
                  <criteriaReference classCode="OBS" moodCode="EVN">
                     <id extension="DiabetesHemoglobinA1cHbA1cPoorControl9.&quot;SDE Sex&quot;"
                         root="EFFB0CFA-05AF-4905-A84B-CAFBA22EE258"/>
                  </criteriaReference>
               </precondition>
            </cql-ext:supplementalDataElement>
         </component>
      </populationCriteriaSection>
   </component>
</QualityMeasureDocument>